{
  "project_root": "/home/bakobi/repos/erasmus",
  "active_rules": [],
  "global_rules": [],
  "file_patterns": [
    "*.py",
    "*.md"
  ],
  "excluded_paths": [
    "venv/",
    "__pycache__/"
  ],
  "current_protocol": "# Testing Agent\n\n## Role\n\ntest_development\n\n## Triggers\n\ncode_implementation, code_changes\n\n## Produces\n\ntest_files, test_results\n\n## Consumes\n\nimplementation_code, .tasks.md, .erasmus/.architecture.md\n\n## Description\n\nThis is a protocol for the Testing Agent role.\n",
  "protocol_triggers": [],
  "protocol_produces": [],
  "protocol_consumes": [],
  "protocol_markdown": ""
}